autocp2k/__init__.py
autocp2k/config.py
autocp2k-0.0.1.dist-info/LICENSE
autocp2k-0.0.1.dist-info/METADATA
autocp2k-0.0.1.dist-info/WHEEL
autocp2k-0.0.1.dist-info/top_level.txt
autocp2k-0.0.1.dist-info/RECORD
