Metadata-Version: 2.1
Name: autocp2k
Version: 0.0.1
Summary: This is a python module for automating CP2K calculations.
Home-page: https://github.com/Cavenfish/autocp2k
Author: Brian C. Ferrari
Author-email: Brian.Ferrari@ucf.edu
License: UNKNOWN
Platform: UNKNOWN
Classifier: Programming Language :: Python :: 3
Classifier: License :: OSI Approved :: MIT License
Classifier: Operating System :: Microsoft :: Windows :: Windows 10
Requires-Dist: numpy
Requires-Dist: scipy
Requires-Dist: pandas
Requires-Dist: basis-set-exchange
Requires-Dist: PeriodicElements
Requires-Dist: openpyxl
Requires-Dist: matplotlib
Requires-Dist: xlrd
Requires-Dist: xlsxwriter
